lintly/__init__.py
lintly/builds.py
lintly/cli.py
lintly/config.py
lintly/constants.py
lintly/exceptions.py
lintly/formatters.py
lintly/parsers.py
lintly/patch.py
lintly/projects.py
lintly/violations.py
lintly/backends/__init__.py
lintly/backends/base.py
lintly/backends/dummy.py
lintly/backends/errors.py
lintly/backends/github.py
lintly/backends/gitlab.py
lintly/backends/objects.py
lintly/templates/check_line_comment.txt
lintly/templates/pr_comment.txt
lintly/templates/pr_review_body.txt
lintly/templates/pr_review_line_comment.txt
lintly-0.6.0.dist-info/LICENSE
lintly-0.6.0.dist-info/METADATA
lintly-0.6.0.dist-info/WHEEL
lintly-0.6.0.dist-info/entry_points.txt
lintly-0.6.0.dist-info/top_level.txt
lintly-0.6.0.dist-info/RECORD
