Metadata-Version: 2.1
Name: lintly
Version: 0.6.0
Summary: Automated GitHub PR code reviewer for Python, JavaScript, CSS, and more.
Home-page: https://github.com/grantmcconnaughey/lintly
Author: Grant McConnaughey
Author-email: grantmcconnaughey@gmail.com
License: MIT
Platform: any
Classifier: Development Status :: 4 - Beta
Classifier: Environment :: Console
Classifier: Intended Audience :: Developers
Classifier: License :: OSI Approved :: MIT License
Classifier: Operating System :: POSIX
Classifier: Operating System :: MacOS
Classifier: Operating System :: Unix
Classifier: Operating System :: Microsoft :: Windows
Classifier: Programming Language :: Python
Classifier: Programming Language :: Python :: 2.7
Classifier: Programming Language :: Python :: 2
Classifier: Programming Language :: Python :: 3
Classifier: Programming Language :: Python :: 3.4
Classifier: Programming Language :: Python :: 3.5
Classifier: Programming Language :: Python :: 3.6
Classifier: Programming Language :: Python :: 3.7
Classifier: Programming Language :: Python :: 3.8
Classifier: Programming Language :: Python :: 3.9
Classifier: Topic :: Software Development :: Libraries :: Python Modules
Classifier: Topic :: Software Development :: Quality Assurance
Requires-Dist: ci-py
Requires-Dist: cached-property (<2.0)
Requires-Dist: click (<8.0)
Requires-Dist: Jinja2 (<3.0)
Requires-Dist: PyGithub (<2.0)
Requires-Dist: python-gitlab (<2.0)
Requires-Dist: six
